setup.py
csvxls/__init__.py
csvxls.egg-info/PKG-INFO
csvxls.egg-info/SOURCES.txt
csvxls.egg-info/dependency_links.txt
csvxls.egg-info/requires.txt
csvxls.egg-info/top_level.txt