Metadata-Version: 1.0
Name: csvxls
Version: 0.1
Summary: Functions to read from CSV or XLS(S) files interchangeably
Home-page: UNKNOWN
Author: Yuki Izumi
Author-email: yuki@kivikakk.ee
License: kindest
Platform: UNKNOWN
